eICU_MEDS/__init__.py
eICU_MEDS/__main__.py
eICU_MEDS/commands.py
eICU_MEDS/dataset.yaml
eICU_MEDS/download.py
eICU_MEDS/pre_MEDS.py
eICU_MEDS/configs/ETL.yaml
eICU_MEDS/configs/__init__.py
eICU_MEDS/configs/event_configs.yaml
eICU_MEDS/configs/main.yaml
eICU_MEDS/configs/runner.yaml
eICU_MEDS/configs/table_preprocessors.yaml
eicu_meds-0.0.2.dist-info/licenses/LICENSE
eicu_meds-0.0.2.dist-info/METADATA
eicu_meds-0.0.2.dist-info/WHEEL
eicu_meds-0.0.2.dist-info/entry_points.txt
eicu_meds-0.0.2.dist-info/top_level.txt
eicu_meds-0.0.2.dist-info/RECORD
